unimonapi/__init__.py
unimonapi/error.py
unimonapi/event.py
unimonapi/host_group.py
unimonapi/monitoring_api.py
unimonapi/zabbix/__init__.py
unimonapi/zabbix/actions.py
unimonapi/zabbix/discovery_rules.py
unimonapi/zabbix/import_export.py
unimonapi/zabbix/lookup.py
unimonapi/zabbix/macros.py
unimonapi/zabbix/zabbix_api.py
unimonapi-0.0.1.data/scripts/zabbix_cli.py
unimonapi-0.0.1.dist-info/LICENSE
unimonapi-0.0.1.dist-info/METADATA
unimonapi-0.0.1.dist-info/WHEEL
unimonapi-0.0.1.dist-info/top_level.txt
unimonapi-0.0.1.dist-info/RECORD
