Metadata-Version: 2.1
Name: unimonapi
Version: 0.0.1
Summary: Universal API for different monitoring systems
Home-page: https://github.com/maxgrechnev/unimonapi
Author: Max Grechnev
Author-email: max.grechnev@gmail.com
License: MIT
Platform: UNKNOWN
Classifier: Programming Language :: Python :: 2.7
Classifier: License :: OSI Approved :: MIT License
Classifier: Operating System :: OS Independent
Requires-Dist: pyzabbix
